homewizard_kitchen-0.4.3.dist-info/licenses/LICENSE.md
hwkitchen/__init__.py
hwkitchen/enums/__init__.py
hwkitchen/enums/kettle_status.py
hwkitchen/models/__init__.py
hwkitchen/models/kettle.py
hwkitchen/services/__init__.py
hwkitchen/services/hw_socket.py
homewizard_kitchen-0.4.3.dist-info/METADATA
homewizard_kitchen-0.4.3.dist-info/WHEEL
homewizard_kitchen-0.4.3.dist-info/top_level.txt
homewizard_kitchen-0.4.3.dist-info/RECORD
