Metadata-Version: 2.4
Name: homewizard-kitchen
Version: 0.4.3
Summary: Manage your Homewizard Kitchen Kettle using Python
Author-email: Lesley De Keyser <me@lesley.eu>
Project-URL: Homepage, https://github.com/lesleyxyz/python-homewizard-kitchen
Project-URL: Bug Tracker, https://github.com/lesleyxyz/python-homewizard-kitchen/issues
Requires-Python: >=3.7
License-File: LICENSE.md
Requires-Dist: websockets>=15.0
Requires-Dist: httpx>=0.28.0
Requires-Dist: jsonpatch>=1.33
Dynamic: license-file
